{
  "updated_at": "2026-03-20T13:40:29.565052Z",
  "spot_price": {
    "date": "2026-03-20",
    "avg_price": 2232.584666530883,
    "max_price": 2890.0,
    "daily_change": 56.5,
    "daily_change_pct": 2.59,
    "volume_kg": 122744.5
  },
  "forecasts": [
    {
      "horizon_days": 1,
      "target_date": "2026-03-21",
      "predicted_price": 2211.9,
      "model_version": "v1.0"
    },
    {
      "horizon_days": 2,
      "target_date": "2026-03-22",
      "predicted_price": 2232.8,
      "model_version": "v1.0"
    },
    {
      "horizon_days": 3,
      "target_date": "2026-03-23",
      "predicted_price": 2239.8,
      "model_version": "v1.0"
    },
    {
      "horizon_days": 4,
      "target_date": "2026-03-24",
      "predicted_price": 2242.1,
      "model_version": "v1.0"
    },
    {
      "horizon_days": 5,
      "target_date": "2026-03-25",
      "predicted_price": 2235.1,
      "model_version": "v1.0"
    },
    {
      "horizon_days": 6,
      "target_date": "2026-03-26",
      "predicted_price": 2315.8,
      "model_version": "v1.0"
    },
    {
      "horizon_days": 7,
      "target_date": "2026-03-27",
      "predicted_price": 2207.2,
      "model_version": "v1.0"
    },
    {
      "horizon_days": 14,
      "target_date": "2026-04-03",
      "predicted_price": 2390.7,
      "model_version": "v1.0"
    },
    {
      "horizon_days": 28,
      "target_date": "2026-04-17",
      "predicted_price": 2365.6,
      "model_version": "v1.0"
    },
    {
      "horizon_days": 90,
      "target_date": "2026-06-18",
      "predicted_price": 2375.8,
      "model_version": "v1.0",
      "lower_bound": 1798.5,
      "upper_bound": 2953.2
    }
  ],
  "regime": {
    "bear_probability": 0.025,
    "label": "LOW",
    "forecast_date": "2026-03-20"
  },
  "model_version": "v1.0"
}